{"nodes": [{"id": "c_users_dell_desktop_projects_lmstax_src_app_admin_modules_page_tsx", "label": "page.tsx", "file_type": "code", "source_file": "C:\\Users\\Dell\\Desktop\\Projects\\lmstax\\src\\app\\admin\\modules\\page.tsx", "source_location": "L1"}, {"id": "modules_page_getmodulelibrary", "label": "getModuleLibrary()", "file_type": "code", "source_file": "C:\\Users\\Dell\\Desktop\\Projects\\lmstax\\src\\app\\admin\\modules\\page.tsx", "source_location": "L28"}, {"id": "modules_page_savemodulelibrary", "label": "saveModuleLibrary()", "file_type": "code", "source_file": "C:\\Users\\Dell\\Desktop\\Projects\\lmstax\\src\\app\\admin\\modules\\page.tsx", "source_location": "L33"}, {"id": "modules_page_handledelete", "label": "handleDelete()", "file_type": "code", "source_file": "C:\\Users\\Dell\\Desktop\\Projects\\lmstax\\src\\app\\admin\\modules\\page.tsx", "source_location": "L52"}, {"id": "modules_page_handleduplicate", "label": "handleDuplicate()", "file_type": "code", "source_file": "C:\\Users\\Dell\\Desktop\\Projects\\lmstax\\src\\app\\admin\\modules\\page.tsx", "source_location": "L59"}], "edges": [{"source": "c_users_dell_desktop_projects_lmstax_src_app_admin_modules_page_tsx", "target": "react", "relation": "imports_from", "context": "import", "confidence": "EXTRACTED", "source_file": "C:\\Users\\Dell\\Desktop\\Projects\\lmstax\\src\\app\\admin\\modules\\page.tsx", "source_location": "L3", "weight": 1.0}, {"source": "c_users_dell_desktop_projects_lmstax_src_app_admin_modules_page_tsx", "target": "link", "relation": "imports_from", "context": "import", "confidence": "EXTRACTED", "source_file": "C:\\Users\\Dell\\Desktop\\Projects\\lmstax\\src\\app\\admin\\modules\\page.tsx", "source_location": "L4", "weight": 1.0}, {"source": "c_users_dell_desktop_projects_lmstax_src_app_admin_modules_page_tsx", "target": "c_users_dell_desktop_projects_lmstax_src_components_admin_adminheader", "relation": "imports_from", "context": "import", "confidence": "EXTRACTED", "source_file": "C:\\Users\\Dell\\Desktop\\Projects\\lmstax\\src\\app\\admin\\modules\\page.tsx", "source_location": "L5", "weight": 1.0}, {"source": "c_users_dell_desktop_projects_lmstax_src_app_admin_modules_page_tsx", "target": "lucide_react", "relation": "imports_from", "context": "import", "confidence": "EXTRACTED", "source_file": "C:\\Users\\Dell\\Desktop\\Projects\\lmstax\\src\\app\\admin\\modules\\page.tsx", "source_location": "L6", "weight": 1.0}, {"source": "c_users_dell_desktop_projects_lmstax_src_app_admin_modules_page_tsx", "target": "modules_page_getmodulelibrary", "relation": "contains", "confidence": "EXTRACTED", "source_file": "C:\\Users\\Dell\\Desktop\\Projects\\lmstax\\src\\app\\admin\\modules\\page.tsx", "source_location": "L28", "weight": 1.0}, {"source": "c_users_dell_desktop_projects_lmstax_src_app_admin_modules_page_tsx", "target": "modules_page_savemodulelibrary", "relation": "contains", "confidence": "EXTRACTED", "source_file": "C:\\Users\\Dell\\Desktop\\Projects\\lmstax\\src\\app\\admin\\modules\\page.tsx", "source_location": "L33", "weight": 1.0}, {"source": "c_users_dell_desktop_projects_lmstax_src_app_admin_modules_page_tsx", "target": "modules_page_handledelete", "relation": "contains", "confidence": "EXTRACTED", "source_file": "C:\\Users\\Dell\\Desktop\\Projects\\lmstax\\src\\app\\admin\\modules\\page.tsx", "source_location": "L52", "weight": 1.0}, {"source": "c_users_dell_desktop_projects_lmstax_src_app_admin_modules_page_tsx", "target": "modules_page_handleduplicate", "relation": "contains", "confidence": "EXTRACTED", "source_file": "C:\\Users\\Dell\\Desktop\\Projects\\lmstax\\src\\app\\admin\\modules\\page.tsx", "source_location": "L59", "weight": 1.0}, {"source": "modules_page_handledelete", "target": "modules_page_savemodulelibrary", "relation": "calls", "context": "call", "confidence": "EXTRACTED", "source_file": "C:\\Users\\Dell\\Desktop\\Projects\\lmstax\\src\\app\\admin\\modules\\page.tsx", "source_location": "L56", "weight": 1.0}, {"source": "modules_page_handleduplicate", "target": "modules_page_savemodulelibrary", "relation": "calls", "context": "call", "confidence": "EXTRACTED", "source_file": "C:\\Users\\Dell\\Desktop\\Projects\\lmstax\\src\\app\\admin\\modules\\page.tsx", "source_location": "L70", "weight": 1.0}], "raw_calls": [{"caller_nid": "modules_page_getmodulelibrary", "callee": "parse", "is_member_call": true, "source_file": "C:\\Users\\Dell\\Desktop\\Projects\\lmstax\\src\\app\\admin\\modules\\page.tsx", "source_location": "L30"}, {"caller_nid": "modules_page_getmodulelibrary", "callee": "getItem", "is_member_call": true, "source_file": "C:\\Users\\Dell\\Desktop\\Projects\\lmstax\\src\\app\\admin\\modules\\page.tsx", "source_location": "L30"}, {"caller_nid": "modules_page_savemodulelibrary", "callee": "setItem", "is_member_call": true, "source_file": "C:\\Users\\Dell\\Desktop\\Projects\\lmstax\\src\\app\\admin\\modules\\page.tsx", "source_location": "L34"}, {"caller_nid": "modules_page_savemodulelibrary", "callee": "stringify", "is_member_call": true, "source_file": "C:\\Users\\Dell\\Desktop\\Projects\\lmstax\\src\\app\\admin\\modules\\page.tsx", "source_location": "L34"}, {"caller_nid": "modules_page_handledelete", "callee": "confirm", "is_member_call": false, "source_file": "C:\\Users\\Dell\\Desktop\\Projects\\lmstax\\src\\app\\admin\\modules\\page.tsx", "source_location": "L53"}, {"caller_nid": "modules_page_handledelete", "callee": "filter", "is_member_call": true, "source_file": "C:\\Users\\Dell\\Desktop\\Projects\\lmstax\\src\\app\\admin\\modules\\page.tsx", "source_location": "L54"}, {"caller_nid": "modules_page_handledelete", "callee": "setModules", "is_member_call": false, "source_file": "C:\\Users\\Dell\\Desktop\\Projects\\lmstax\\src\\app\\admin\\modules\\page.tsx", "source_location": "L55"}, {"caller_nid": "modules_page_handleduplicate", "callee": "now", "is_member_call": true, "source_file": "C:\\Users\\Dell\\Desktop\\Projects\\lmstax\\src\\app\\admin\\modules\\page.tsx", "source_location": "L62"}, {"caller_nid": "modules_page_handleduplicate", "callee": "map", "is_member_call": true, "source_file": "C:\\Users\\Dell\\Desktop\\Projects\\lmstax\\src\\app\\admin\\modules\\page.tsx", "source_location": "L64"}, {"caller_nid": "modules_page_handleduplicate", "callee": "toISOString", "is_member_call": true, "source_file": "C:\\Users\\Dell\\Desktop\\Projects\\lmstax\\src\\app\\admin\\modules\\page.tsx", "source_location": "L65"}, {"caller_nid": "modules_page_handleduplicate", "callee": "toISOString", "is_member_call": true, "source_file": "C:\\Users\\Dell\\Desktop\\Projects\\lmstax\\src\\app\\admin\\modules\\page.tsx", "source_location": "L66"}, {"caller_nid": "modules_page_handleduplicate", "callee": "setModules", "is_member_call": false, "source_file": "C:\\Users\\Dell\\Desktop\\Projects\\lmstax\\src\\app\\admin\\modules\\page.tsx", "source_location": "L69"}]}